conwaymd/__init__.py
conwaymd/_version.py
conwaymd/authorities.py
conwaymd/bases.py
conwaymd/cli.py
conwaymd/constants.py
conwaymd/core.py
conwaymd/employables.py
conwaymd/exceptions.py
conwaymd/idioms.py
conwaymd/placeholders.py
conwaymd/references.py
conwaymd/utilities.py
conwaymd-6.0.0.dist-info/entry_points.txt
conwaymd-6.0.0.dist-info/licenses/LICENSE
conwaymd-6.0.0.dist-info/WHEEL
conwaymd-6.0.0.dist-info/METADATA
conwaymd-6.0.0.dist-info/RECORD
