Metadata-Version: 2.4
Name: conwaymd
Version: 6.0.0
Summary: Conway-Markdown (conwaymd, CMD)
Keywords: conway-markdown,html5
Author-email: Conway <pypi.sheep257@passmail.net>
Requires-Python: >=3.11
Classifier: Programming Language :: Python :: 3
Classifier: Programming Language :: Python :: 3.11
Classifier: Programming Language :: Python :: 3.12
Classifier: License :: OSI Approved :: MIT No Attribution License (MIT-0)
Classifier: Operating System :: OS Independent
License-File: LICENSE
Project-URL: changelog, https://github.com/conwaymd/conwaymd/blob/master/CHANGELOG.md
Project-URL: homepage, https://conwaymd.github.io/
Project-URL: issues, https://github.com/conwaymd/conwaymd/issues
Project-URL: repository, https://github.com/conwaymd/conwaymd
